notification_mcp/__init__.py
notification_mcp/server.py
notification_mcp_shao-1.0.0.dist-info/METADATA
notification_mcp_shao-1.0.0.dist-info/WHEEL
notification_mcp_shao-1.0.0.dist-info/entry_points.txt
notification_mcp_shao-1.0.0.dist-info/RECORD
