Metadata-Version: 2.4
Name: notification-mcp-shao
Version: 1.0.0
Summary: MCP server for email and DingTalk notifications
Author-email: shao <18168352057@163.com>
Requires-Python: >=3.10
Requires-Dist: mcp>=0.9.0
Requires-Dist: python-dotenv>=1.0.0
Requires-Dist: requests>=2.31.0
